README.rst
setup.py
AuthorizeSauce.egg-info/PKG-INFO
AuthorizeSauce.egg-info/SOURCES.txt
AuthorizeSauce.egg-info/dependency_links.txt
AuthorizeSauce.egg-info/requires.txt
AuthorizeSauce.egg-info/top_level.txt
authorize/__init__.py
authorize/client.py
authorize/data.py
authorize/exceptions.py
authorize/apis/__init__.py
authorize/apis/customer.py
authorize/apis/recurring.py
authorize/apis/transaction.py