Metadata-Version: 1.1
Name: AuthorizeSauce
Version: 0.3.3
Summary: An awesome-sauce Python library for accessing the Authorize.net API. Sweet!
Home-page: http://authorize-sauce.readthedocs.org/
Author: Jeff Schenck
Author-email: jmschenck@gmail.com
License: MIT
Download-URL: https://github.com/jeffschenck/authorizesauce
Platform: UNKNOWN
Classifier: Development Status :: 4 - Beta
Classifier: Environment :: Console
Classifier: Environment :: Web Environment
Classifier: Intended Audience :: Developers
Classifier: Programming Language :: Python :: 2
Classifier: License :: OSI Approved :: MIT License
Classifier: Topic :: Office/Business :: Financial
Classifier: Topic :: Internet :: WWW/HTTP
